python_text_menu/__init__.py
python_text_menu/menu.py
python_text_menu-0.0.5.dist-info/METADATA
python_text_menu-0.0.5.dist-info/WHEEL
python_text_menu-0.0.5.dist-info/top_level.txt
python_text_menu-0.0.5.dist-info/RECORD
