Metadata-Version: 2.1
Name: python-text-menu
Version: 0.0.5
Summary: Basic text menu for console
Home-page: UNKNOWN
Author: Macaya25 (Andres Macaya)
Author-email: afmacaya@miuandes.cl
License: UNKNOWN
Keywords: python,menu,cli
Platform: UNKNOWN
